abm_colony_collection/__init__.py
abm_colony_collection/__main__.py
abm_colony_collection/calculate_centrality_measures.py
abm_colony_collection/calculate_degree_measures.py
abm_colony_collection/calculate_distance_measures.py
abm_colony_collection/convert_to_network.py
abm_colony_collection/get_depth_map.py
abm_colony_collection/get_neighbors_map.py
abm_colony_collection/make_voxels_array.py
abm_colony_collection/py.typed
abm_colony_collection-0.5.0.dist-info/LICENSE
abm_colony_collection-0.5.0.dist-info/METADATA
abm_colony_collection-0.5.0.dist-info/WHEEL
abm_colony_collection-0.5.0.dist-info/RECORD
