Metadata-Version: 2.1
Name: abm-colony-collection
Version: 0.5.0
Summary: Collection of tasks for analyzing colony dynamics.
License: BSD-3-Clause
Author: Jessica S. Yu
Author-email: jesyu@uw.edu
Requires-Python: >=3.9,<4.0
Classifier: License :: OSI Approved :: BSD License
Classifier: Programming Language :: Python :: 3
Classifier: Programming Language :: Python :: 3.9
Classifier: Programming Language :: Python :: 3.10
Classifier: Programming Language :: Python :: 3.11
Classifier: Programming Language :: Python :: 3.12
Requires-Dist: networkx (>=3.0,<4.0)
Requires-Dist: numpy (>=1.24.2,<2.0.0)
Requires-Dist: pandas (>=1.5.3,<2.0.0)
Requires-Dist: prefect (>=2.8.2,<3.0.0)
Requires-Dist: scikit-image (>=0.21.0,<0.22.0)
Requires-Dist: scipy (>=1.9.3,<2.0.0)
